dimjournal/__init__.py
dimjournal/__main__.py
dimjournal/dimjournal.py
dimjournal-1.0.9.dist-info/LICENSE.txt
dimjournal-1.0.9.dist-info/METADATA
dimjournal-1.0.9.dist-info/WHEEL
dimjournal-1.0.9.dist-info/entry_points.txt
dimjournal-1.0.9.dist-info/top_level.txt
dimjournal-1.0.9.dist-info/RECORD
