Metadata-Version: 2.1
Name: dimjournal
Version: 1.0.9
Summary: Archive utility for Midjourney
Home-page: https://pypi.org/project/dimjournal/
Author: Adam Twardoch
Author-email: adam+github@twardoch.com
License: Apache-2.0
Project-URL: Documentation, https://twardoch.github.io/dimjournal/
Project-URL: Source, https://github.com/twardoch/dimjournal
Project-URL: Download, https://pypi.org/project/dimjournal
Platform: any
Classifier: Development Status :: 4 - Beta
Classifier: Programming Language :: Python
Classifier: Topic :: Software Development :: Libraries :: Python Modules
Classifier: License :: OSI Approved :: Apache Software License
Classifier: Operating System :: OS Independent
License-File: LICENSE.txt
Requires-Dist: beautifulsoup4 (>=4.12.2)
Requires-Dist: fire (>=0.5.0)
Requires-Dist: numpy (>=1.25.0)
Requires-Dist: Pillow (>=10.0.0)
Requires-Dist: pymtpng (>=1.0)
Requires-Dist: pytest (>=7.3.1)
Requires-Dist: python-slugify (>=8.0.1)
Requires-Dist: selenium (>=4.10.0)
Requires-Dist: setuptools (>=67.6.1)
Requires-Dist: tqdm (>=4.65.0)
Requires-Dist: undetected-chromedriver (>=3.5.0)
Provides-Extra: testing
Requires-Dist: setuptools ; extra == 'testing'
Requires-Dist: pytest ; extra == 'testing'
Requires-Dist: pytest-cov ; extra == 'testing'
